types_aiobotocore_macie/__init__.py
types_aiobotocore_macie/__init__.pyi
types_aiobotocore_macie/__main__.py
types_aiobotocore_macie/client.py
types_aiobotocore_macie/client.pyi
types_aiobotocore_macie/literals.py
types_aiobotocore_macie/literals.pyi
types_aiobotocore_macie/paginator.py
types_aiobotocore_macie/paginator.pyi
types_aiobotocore_macie/py.typed
types_aiobotocore_macie/type_defs.py
types_aiobotocore_macie/type_defs.pyi
types_aiobotocore_macie/version.py
types_aiobotocore_macie-2.7.0.dist-info/LICENSE
types_aiobotocore_macie-2.7.0.dist-info/METADATA
types_aiobotocore_macie-2.7.0.dist-info/WHEEL
types_aiobotocore_macie-2.7.0.dist-info/top_level.txt
types_aiobotocore_macie-2.7.0.dist-info/RECORD
